bigdatacloudapi/__init__.py
bigdatacloudapi/client.py
bigdatacloudapi_client-1.0.3.dist-info/LICENSE
bigdatacloudapi_client-1.0.3.dist-info/METADATA
bigdatacloudapi_client-1.0.3.dist-info/WHEEL
bigdatacloudapi_client-1.0.3.dist-info/top_level.txt
bigdatacloudapi_client-1.0.3.dist-info/RECORD
