Metadata-Version: 2.1
Name: bigdatacloudapi-client
Version: 1.0.3
Summary: A Python client for BigDataCloud API connectivity (https://www.bigdatacloud.com)
Home-page: https://github.com/bigdatacloudapi/python-api-client
Author: BigDataCloud
Author-email: support@bigdatacloud.com
License: MIT
Classifier: License :: OSI Approved :: MIT License
Classifier: Programming Language :: Python
Classifier: Programming Language :: Python :: 2
Classifier: Programming Language :: Python :: 3
License-File: LICENSE
Requires-Dist: requests
